setup.py
MegaMess_client.egg-info/PKG-INFO
MegaMess_client.egg-info/SOURCES.txt
MegaMess_client.egg-info/dependency_links.txt
MegaMess_client.egg-info/requires.txt
MegaMess_client.egg-info/top_level.txt
client/__init__.py
client/client_main.py
client/database_client.py
client/encrypt_decrypt.py
client/common/__init__.py
client/common/decos.py
client/common/descriptors.py
client/common/errors.py
client/common/metaclasses.py
client/common/utils.py
client/common/variables.py
client/gui_client/__init__.py
client/gui_client/add_contact_config.py
client/gui_client/del_contact_config.py
client/gui_client/gui_add_contact.py
client/gui_client/gui_del_contact.py
client/gui_client/gui_loading_dialog.py
client/gui_client/gui_main_window.py
client/gui_client/gui_start_dialog.py
client/gui_client/loading_config.py
client/gui_client/main_window_config.py
client/gui_client/start_dialog_config.py
client/logs/__init__.py
client/logs/client_log_config.py
client/logs/files_log/__init__.py
client/main/__init__.py