Metadata-Version: 1.0
Name: MegaMess-client
Version: 0.8.3
Summary: Mega messenger client
Home-page: UNKNOWN
Author: Maria Afanaseva
Author-email: mashenkachukina@gmail.com
License: UNKNOWN
Platform: UNKNOWN
